mcp_http_proxy/__init__.py
mcp_http_proxy/py.typed
mcp_http_proxy-0.0.0.dist-info/METADATA
mcp_http_proxy-0.0.0.dist-info/WHEEL
mcp_http_proxy-0.0.0.dist-info/licenses/LICENSE
mcp_http_proxy-0.0.0.dist-info/RECORD
